LabToolbox/__init__.py
LabToolbox/_helper.py
LabToolbox/_uncertainty_class.py
LabToolbox/fit.py
LabToolbox/io.py
LabToolbox/signals.py
LabToolbox/stats.py
LabToolbox/uncertainty.py
LabToolbox/utils.py
docs/test.py
labtoolbox-3.0.0.dist-info/METADATA
labtoolbox-3.0.0.dist-info/WHEEL
labtoolbox-3.0.0.dist-info/top_level.txt
labtoolbox-3.0.0.dist-info/RECORD
