Metadata-Version: 2.4
Name: LabToolbox
Version: 3.0.0
Summary: A Python package for the analysis and processing of experimental data in scientific research.
Author-email: Giuseppe Sorrentino <sorrentinogiuse@icloud.com>
License-Expression: MIT
Project-URL: Documentation, https://github.com/giusesorrentino/LabToolbox/wiki
Project-URL: Source, https://github.com/giusesorrentino/LabToolbox
Project-URL: Tracker, https://github.com/giusesorrentino/LabToolbox/issues
Project-URL: Changelog, https://github.com/giusesorrentino/LabToolbox/releases
Classifier: Programming Language :: Python :: 3
Classifier: Operating System :: OS Independent
Requires-Python: >=3.9.6
Requires-Dist: numpy
Requires-Dist: scipy
Requires-Dist: matplotlib
Requires-Dist: statsmodels
Requires-Dist: emcee
Requires-Dist: corner
Requires-Dist: lmfit
Requires-Dist: astropy
